extra_data/__init__.py
extra_data/aliases.py
extra_data/auxiliary.py
extra_data/components.py
extra_data/compression.py
extra_data/copy.py
extra_data/exceptions.py
extra_data/export.py
extra_data/file_access.py
extra_data/keydata.py
extra_data/locality.py
extra_data/read_machinery.py
extra_data/reader.py
extra_data/run_files_map.py
extra_data/sourcedata.py
extra_data/stacking.py
extra_data/utils.py
extra_data/validation.py
extra_data/voview.py
extra_data/write_cxi.py
extra_data/writer.py
extra_data/cli/__init__.py
extra_data/cli/check_readable.py
extra_data/cli/lsxfel.py
extra_data/cli/make_virtual_cxi.py
extra_data/cli/serve_files.py
extra_data/cli/serve_run.py
extra_data/tests/__init__.py
extra_data/tests/conftest.py
extra_data/tests/make_examples.py
extra_data/tests/test_aliases.py
extra_data/tests/test_auxiliary.py
extra_data/tests/test_bad_trains.py
extra_data/tests/test_components.py
extra_data/tests/test_compression.py
extra_data/tests/test_copy.py
extra_data/tests/test_file_access.py
extra_data/tests/test_keydata.py
extra_data/tests/test_lsxfel.py
extra_data/tests/test_mockdata.py
extra_data/tests/test_open_file_limiter.py
extra_data/tests/test_open_run.py
extra_data/tests/test_read_machinery.py
extra_data/tests/test_reader_mockdata.py
extra_data/tests/test_run_files_map.py
extra_data/tests/test_slice_objs.py
extra_data/tests/test_sourcedata.py
extra_data/tests/test_stacking.py
extra_data/tests/test_streamer.py
extra_data/tests/test_validation.py
extra_data/tests/test_voview.py
extra_data/tests/test_writer.py
extra_data/tests/cli/__init__.py
extra_data/tests/cli/test_check_readable.py
extra_data/tests/cli/test_make_virtual_cxi.py
extra_data/tests/mockdata/__init__.py
extra_data/tests/mockdata/adc.py
extra_data/tests/mockdata/agipd.py
extra_data/tests/mockdata/auxiliary.py
extra_data/tests/mockdata/base.py
extra_data/tests/mockdata/basler_camera.py
extra_data/tests/mockdata/control_common.py
extra_data/tests/mockdata/dctrl.py
extra_data-1.23.2.dist-info/licenses/LICENSE
extra_data-1.23.2.dist-info/METADATA
extra_data-1.23.2.dist-info/WHEEL
extra_data-1.23.2.dist-info/entry_points.txt
extra_data-1.23.2.dist-info/top_level.txt
extra_data-1.23.2.dist-info/RECORD
