Metadata-Version: 2.4
Name: EXtra-data
Version: 1.23.2
Summary: Tools to read and analyse data from European XFEL 
Author: European XFEL GmbH
Author-email: da-support@xfel.eu
Maintainer: Thomas Michelat
License: BSD-3-Clause
Project-URL: Documentation, https://extra-data.readthedocs.io/en/latest/
Project-URL: Release notes, https://extra-data.readthedocs.io/en/latest/changelog.html
Project-URL: Issues, https://github.com/European-XFEL/EXtra-data/issues
Project-URL: Source, https://github.com/European-XFEL/EXtra-data
Classifier: Development Status :: 5 - Production/Stable
Classifier: Environment :: Console
Classifier: Intended Audience :: Developers
Classifier: Intended Audience :: Science/Research
Classifier: License :: OSI Approved :: BSD License
Classifier: Operating System :: POSIX :: Linux
Classifier: Programming Language :: Python :: 3
Classifier: Topic :: Scientific/Engineering :: Information Analysis
Classifier: Topic :: Scientific/Engineering :: Physics
Requires-Python: >=3.10
License-File: LICENSE
Requires-Dist: h5py>=2.10
Requires-Dist: matplotlib
Requires-Dist: numpy
Requires-Dist: packaging
Requires-Dist: pandas
Requires-Dist: xarray
Requires-Dist: pyyaml
Provides-Extra: bridge
Requires-Dist: karabo-bridge>=0.6; extra == "bridge"
Requires-Dist: psutil; extra == "bridge"
Provides-Extra: complete
Requires-Dist: dask[array]; extra == "complete"
Requires-Dist: extra_data[bridge]; extra == "complete"
Requires-Dist: tomli; python_version < "3.11" and extra == "complete"
Requires-Dist: zlib_into>=0.4; extra == "complete"
Provides-Extra: docs
Requires-Dist: extra_data[bridge]; extra == "docs"
Requires-Dist: ipython; extra == "docs"
Requires-Dist: nbsphinx; extra == "docs"
Requires-Dist: sphinx; extra == "docs"
Requires-Dist: sphinx-rtd-theme; extra == "docs"
Requires-Dist: sphinxcontrib_github_alt; extra == "docs"
Requires-Dist: readthedocs-sphinx-search; extra == "docs"
Provides-Extra: test
Requires-Dist: cloudpickle; extra == "test"
Requires-Dist: coverage; extra == "test"
Requires-Dist: extra_data[complete]; extra == "test"
Requires-Dist: nbval; extra == "test"
Requires-Dist: pytest; extra == "test"
Requires-Dist: pytest-cov; extra == "test"
Requires-Dist: testpath; extra == "test"
Dynamic: author
Dynamic: author-email
Dynamic: classifier
Dynamic: description
Dynamic: description-content-type
Dynamic: license
Dynamic: license-file
Dynamic: maintainer
Dynamic: project-url
Dynamic: provides-extra
Dynamic: requires-dist
Dynamic: requires-python
Dynamic: summary
